<?xml version='1.0' encoding='UTF-8'?>
<persona>
  <basic_stats>
    <name>Futsunushi</name>
    <level>80</level>
    <arcana>Chariot</arcana>
    <alignment>INVALID ALIGNMENT</alignment>
  </basic_stats>
  <basic_attributes>
    <strength>59</strength>
    <magic>38</magic>
    <endurance>61</endurance>
    <agility>44</agility>
    <luck>45</luck>
  </basic_attributes>
  <elemental_properties>
    <inherit>Phys</inherit>
    <resist>-</resist>
    <block>Phys</block>
    <absorb>-</absorb>
    <reflect>-</reflect>
    <weakness>Dark</weakness>
  </elemental_properties>
  <information>Futsunushi-no-kami (経津主神) is a Shinto kami of swords. He is regarded as the personification of the sword Futsu-no-mitama.</information>
  <skilltree>
    <skill>
      <name>Primal Force</name>
      <learned>Innate</learned>
    </skill>
    <skill>
      <name>Power Charge</name>
      <learned>Innate</learned>
    </skill>
    <skill>
      <name>Matarukaja</name>
      <learned>Innate</learned>
    </skill>
    <skill>
      <name>Apt Pupil</name>
      <learned>82</learned>
    </skill>
    <skill>
      <name>Null Dizzy</name>
      <learned>83</learned>
    </skill>
    <skill>
      <name>Ali Dance</name>
      <learned>84</learned>
    </skill>
    <skill>
      <name>Arms Master</name>
      <learned>85</learned>
    </skill>
    <skill>
      <name>Firm Stance</name>
      <learned>86</learned>
    </skill>
  </skilltree>
</persona>

