<?xml version='1.0' encoding='UTF-8'?>
<persona>
  <basic_stats>
    <name>Tam Lin</name>
    <level>53</level>
    <arcana>Sun</arcana>
    <alignment>Neutral Good</alignment>
  </basic_stats>
  <basic_attributes>
    <strength>45</strength>
    <magic>31</magic>
    <endurance>34</endurance>
    <agility>39</agility>
    <luck>25</luck>
  </basic_attributes>
  <elemental_properties>
    <inherit>Light/Fire</inherit>
    <resist>Physical/Fire</resist>
    <block>Light</block>
    <absorb>-</absorb>
    <reflect>-</reflect>
    <weakness>-</weakness>
  </elemental_properties>
  <information>A famous fairy who was said to haunt Caterhaugh Wood in England. He supposedly lured young women away to ruin them. He was once a human who had been trapped by the Fairy Queen. A young woman named Janet is said to have fallen in love with him at one point, and finally managed to free him.</information>
  <skilltree>
    <skill>
      <name>Ziodyne</name>
      <learned>Innate</learned>
    </skill>
    <skill>
      <name>Deathbound</name>
      <learned>Innate</learned>
    </skill>
    <skill>
      <name>High Counter</name>
      <learned>Innate</learned>
    </skill>
    <skill>
      <name>Auto-Maraku</name>
      <learned>54</learned>
    </skill>
    <skill>
      <name>Power Charge</name>
      <learned>55</learned>
    </skill>
    <skill>
      <name>Elec Amp</name>
      <learned>56</learned>
    </skill>
    <skill>
      <name>Evade Physical</name>
      <learned>58</learned>
    </skill>
    <skill>
      <name>Enduring Soul</name>
      <learned>59</learned>
    </skill>
  </skilltree>
</persona>

